odoo/addons/sale_product_set_packaging_qty/README.rst
odoo/addons/sale_product_set_packaging_qty/__init__.py
odoo/addons/sale_product_set_packaging_qty/__manifest__.py
odoo/addons/sale_product_set_packaging_qty/i18n/es.po
odoo/addons/sale_product_set_packaging_qty/i18n/it.po
odoo/addons/sale_product_set_packaging_qty/i18n/sale_product_set_packaging_qty.pot
odoo/addons/sale_product_set_packaging_qty/models/__init__.py
odoo/addons/sale_product_set_packaging_qty/models/product_set.py
odoo/addons/sale_product_set_packaging_qty/readme/CONTRIBUTORS.md
odoo/addons/sale_product_set_packaging_qty/readme/CREDITS.md
odoo/addons/sale_product_set_packaging_qty/readme/DESCRIPTION.md
odoo/addons/sale_product_set_packaging_qty/static/description/icon.png
odoo/addons/sale_product_set_packaging_qty/static/description/index.html
odoo/addons/sale_product_set_packaging_qty/tests/__init__.py
odoo/addons/sale_product_set_packaging_qty/tests/test_product_set_packaging.py
odoo_addon_sale_product_set_packaging_qty-18.0.1.0.0.2.dist-info/METADATA
odoo_addon_sale_product_set_packaging_qty-18.0.1.0.0.2.dist-info/WHEEL
odoo_addon_sale_product_set_packaging_qty-18.0.1.0.0.2.dist-info/top_level.txt
odoo_addon_sale_product_set_packaging_qty-18.0.1.0.0.2.dist-info/RECORD
